youtube_transcript_extractor/__init__.py
youtube_transcript_extractor/extractor.py
youtube_transcript_extractor-0.1.4.dist-info/licenses/LICENSE
youtube_transcript_extractor-0.1.4.dist-info/METADATA
youtube_transcript_extractor-0.1.4.dist-info/WHEEL
youtube_transcript_extractor-0.1.4.dist-info/top_level.txt
youtube_transcript_extractor-0.1.4.dist-info/RECORD
