Metadata-Version: 2.4
Name: youtube-transcript-extractor
Version: 0.1.4
Summary: A Python package to extract and clean YouTube video transcripts easily.
Author-email: 54gO <sagar8296d@gmail.com>
License: LICENSE
Requires-Python: >=3.9
License-File: LICENSE
Requires-Dist: youtube-transcript-api>=0.6.0
Requires-Dist: urllib3>=1.26.0
Requires-Dist: requests>=2.28.0
Dynamic: license-file
